stepwise_regression/__init__.py
stepwise_regression/step_reg.py
stepwise_regression/stepwise_regression.py
stepwise_regression-1.0.3.dist-info/METADATA
stepwise_regression-1.0.3.dist-info/RECORD
stepwise_regression-1.0.3.dist-info/WHEEL
stepwise_regression-1.0.3.dist-info/top_level.txt
