Metadata-Version: 2.1
Name: stepwise-regression
Version: 1.0.3
Summary: A Python package to implement stepwise regression
Home-page: https://github.com/AakkashVijayakumar/stepwise-regression
Author: Aakkash Vijayakumar
Author-email: aakkashvijayakumar@gmail.com
License: MIT
Platform: UNKNOWN
Classifier: License :: OSI Approved :: MIT License
Classifier: Programming Language :: Python :: 3
Classifier: Programming Language :: Python :: 3.7
Requires-Dist: statsmodels
Requires-Dist: pandas
